bernoulli_moivre/__init__.py
bernoulli_moivre/bernoulli/__init__.py
bernoulli_moivre/bernoulli/bernoulli.py
bernoulli_moivre/moivre_laplace/__init__.py
bernoulli_moivre/moivre_laplace/moivre_laplace.py
tests/__init__.py
tests/test_bernoulli.py
tests/test_moivre_laplace.py
bernoulli_moivre-0.1.2.dist-info/METADATA
bernoulli_moivre-0.1.2.dist-info/WHEEL
bernoulli_moivre-0.1.2.dist-info/top_level.txt
bernoulli_moivre-0.1.2.dist-info/RECORD
