Metadata-Version: 2.4
Name: bernoulli-moivre
Version: 0.1.2
Summary: Bernoulli and Moivre–Laplace probability formulas
Author-email: 1032240005 <1032240005@pfur.ru>, 1132240693 <1132240693@pfur.ru>
Classifier: Programming Language :: Python :: 3
Classifier: Operating System :: OS Independent
Requires-Python: >=3.9
Provides-Extra: test
Requires-Dist: pytest; extra == "test"
